README.md
setup.cfg
setup.py
lets/__about__.py
lets/__init__.py
lets/alarm.py
lets/atomicity.py
lets/jobqueue.py
lets/objectpool.py
lets/processlet.py
lets/quietlet.py
lets/slavery.py
lets/transparentlet.py
lets/utils.py
lets.egg-info/PKG-INFO
lets.egg-info/SOURCES.txt
lets.egg-info/dependency_links.txt
lets.egg-info/not-zip-safe
lets.egg-info/requires.txt
lets.egg-info/top_level.txt